{
  "malos": [
    {
      "date": "10 Dic 2010", 
      "ranking": {
        "Servicio": 1, 
        "Ambiente": 2, 
        "Comida": 1
      }, 
      "user_name": "Nirius", 
      "text": "Fuimos por el cumplea\u00f1os de un amigo, y lo agarramos como segunda opci\u00f3n al no tener lugar enfrente. \r\nPed\u00ed la comida y si bien la chica era muy simp\u00e1tica y buena onda, tardaron 30 minutos en traer un pollo salteado con vegetales, que supuestamente ten\u00eda salsa de soja y miel (s\u00f3lo detect\u00e9 la salsa de soja ya que estaba hiper salado y dej\u00e9 el arroz de la base, que era incomible por la cantidad de salsa)."
    }
  ], 
  "buenos": [
    {
      "date": "20 Dic 2010", 
      "ranking": {
        "Servicio": 2, 
        "Ambiente": 2, 
        "Comida": 2
      }, 
      "user_name": "elpibetigre", 
      "text": "Lindo lugar, sobre todo la terraza. La pizza correcta, las empanadas me parecieron mas ricas. Buena atenci\u00f3n."
    }, 
    {
      "date": "22 Nov 2010", 
      "ranking": {
        "Servicio": 3, 
        "Ambiente": 2, 
        "Comida": 3
      }, 
      "user_name": "sibaritatrip", 
      "text": "Es una opci\u00f3n m\u00e1s que aceptable si uno no quiere pagar de m\u00e1s por una pizza, las pastas son muy buenas y la atenci\u00f3n es muy esmerada. No es un lugar donde se destaca la pizza gourmet, pero la comida es de muy buena calidad y la relaci\u00f3n precio/producto es muy razonable.\r\nEs una muy buena opci\u00f3n."
    }, 
    {
      "date": "8 Oct 2010", 
      "ranking": {
        "Servicio": 2, 
        "Ambiente": 2, 
        "Comida": 2
      }, 
      "user_name": "Martu75", 
      "text": "Para un almuerzo de un viernes, pedimos una buena pizza rellena de fugazza con queso. La atenci\u00f3n de la moza fue correcta, el lugar muy tranquilo y el precio normal."
    }, 
    {
      "date": "11 Sep 2010", 
      "ranking": {
        "Servicio": 2, 
        "Ambiente": 2, 
        "Comida": 2
      }, 
      "user_name": "Virra", 
      "text": "Llegamos a las 22:30 y nos trajeron la comida a las 24:30. No tuvieron la delicadeza de decirnos que hab\u00eda faltado el ayudante de cocina antes de hacer el pedido ni durante la espera, reci\u00e9n lo hicieron la segunda vez que preguntamos. \u00c9ramos 6 comensales y la \u00fanica atenci\u00f3n que tuvieron fue traernos una cerveza de m\u00e1s. La cuenta nos la cobraron enterita sin ning\u00fan descuento por las 2 horas de espera. Alguien del personal puede tener alg\u00fan imprevisto y faltar, pero el encargado del local o due\u00f1o deber\u00eda resolver el tema cuidando un poco m\u00e1s al cliente. Definitivamente para no volver."
    }, 
    {
      "date": "5 Ago 2010", 
      "ranking": {
        "Servicio": 1, 
        "Ambiente": 2, 
        "Comida": 2
      }, 
      "user_name": "BelR", 
      "text": "Es un lindo lugar que podria tener m\u00e1s onda, le falta un poco de musica y gente! La pizza no es gran cosa, nada espectacular, tirando a \"com\u00fan\". Habia solo dos mesas ocupadas y nos trajeron mal lo que pedimos y frio, la moza atenta pero la encargada estaba chateando por lo que tardo 15 minutos en darse cuenta que le estabamos pidiendo la cuenta. Si estan de paso y tienen hambre entren, pero sino no es un lugar que volveria a elegir para ir, hay mejores en la misma zona."
    }, 
    {
      "date": "1 Jun 2010", 
      "ranking": {
        "Servicio": 2, 
        "Ambiente": 2, 
        "Comida": 2
      }, 
      "user_name": "leeleebee", 
      "text": "la ambientaci\u00f3n del lugar es agradable y el servicio correcto. la comida aceptable aunque no m\u00e1s que eso: no sabrosa, no gourmet, nada destacable. Econ\u00f3mico el men\u00fa de mediod\u00eda, pero con tanta oferta en la zona de Palermo, no da para repetir."
    }
  ]
}